python_supercluster/__init__.py
python_supercluster/kdbush.py
python_supercluster/supercluster.py
tests/__init__.py
tests/fixtures.py
tests/test_supercluster.py
python_supercluster-0.0.1.dist-info/LICENSE
python_supercluster-0.0.1.dist-info/METADATA
python_supercluster-0.0.1.dist-info/WHEEL
python_supercluster-0.0.1.dist-info/top_level.txt
python_supercluster-0.0.1.dist-info/RECORD
